docker_image_size_limit/__init__.py
docker_image_size_limit/__main__.py
docker_image_size_limit/py.typed
docker_image_size_limit/version.py
docker_image_size_limit-2.2.0.dist-info/LICENSE
docker_image_size_limit-2.2.0.dist-info/METADATA
docker_image_size_limit-2.2.0.dist-info/WHEEL
docker_image_size_limit-2.2.0.dist-info/entry_points.txt
docker_image_size_limit-2.2.0.dist-info/RECORD
