Metadata-Version: 2.3
Name: docker-image-size-limit
Version: 2.2.0
Summary: 
License: MIT
Keywords: docker,docker image,size limit,wemake.services,code quality
Author: Nikita Sobolev
Author-email: mail@sobolevn.me
Requires-Python: >=3.10,<4.0
Classifier: Development Status :: 5 - Production/Stable
Classifier: Environment :: Console
Classifier: Intended Audience :: Developers
Classifier: License :: OSI Approved :: MIT License
Classifier: Operating System :: OS Independent
Classifier: Programming Language :: Python :: 3
Classifier: Programming Language :: Python :: 3.10
Classifier: Programming Language :: Python :: 3.11
Classifier: Programming Language :: Python :: 3.12
Classifier: Programming Language :: Python :: 3.13
Classifier: Topic :: Software Development :: Libraries :: Python Modules
Classifier: Topic :: Software Development :: Quality Assurance
Classifier: Typing :: Typed
Requires-Dist: docker (>=3.7)
Requires-Dist: humanfriendly (>=4.18,<11.0)
Project-URL: Funding, https://github.com/sponsors/wemake-services
Project-URL: Repository, https://github.com/wemake-services/docker-image-size-limit
